README.md
setup.py
datastructs/__init__.py
datastructs/linked_list.py
datastructs/trees.py
datastructs.egg-info/PKG-INFO
datastructs.egg-info/SOURCES.txt
datastructs.egg-info/dependency_links.txt
datastructs.egg-info/not-zip-safe
datastructs.egg-info/top_level.txt
datastructs/tests/__init__.py
datastructs/tests/test_linked_list.py
datastructs/tests/test_trees.py