Metadata-Version: 2.1
Name: datastructs
Version: 0.2.2
Summary: Module created to facilitate the creation and use of data structures
Home-page: https://github.com/barthjr/datastructs
Author: Junior Barth
Author-email: juniior.barth@gmail.com
License: AGPLv3+
Platform: UNKNOWN
Classifier: Development Status :: 2 - Pre-Alpha
Classifier: Environment :: Console
Classifier: Intended Audience :: Developers
Classifier: License :: OSI Approved :: GNU Affero General Public License v3 or later (AGPLv3+)
Classifier: Operating System :: OS Independent
Classifier: Programming Language :: Python
Classifier: Programming Language :: Python :: 3.7
Classifier: Framework :: Pytest
